zipline_extensions/__init__.py
zipline_extensions/_version.py
zipline_extensions/errors.py
zipline_extensions/data/__init__.py
zipline_extensions/data/bundles/__init__.py
zipline_extensions/data/bundles/history.py
zipline_extensions/data/bundles/tests.py
zipline_extensions/pipeline/__init__.py
zipline_extensions/pipeline/data/__init__.py
zipline_extensions/pipeline/data/fundamental.py
quantrocket_zipline_extensions-1.4.0.dist-info/LICENSE.txt
quantrocket_zipline_extensions-1.4.0.dist-info/METADATA
quantrocket_zipline_extensions-1.4.0.dist-info/WHEEL
quantrocket_zipline_extensions-1.4.0.dist-info/top_level.txt
quantrocket_zipline_extensions-1.4.0.dist-info/RECORD
