Metadata-Version: 2.1
Name: quantrocket-zipline-extensions
Version: 1.4.0
Summary: Zipline for QuantRocket
Home-page: https://www.quantrocket.com
Author: QuantRocket LLC
Author-email: support@quantrocket.com
License: Apache-2.0
Platform: UNKNOWN
